Workbook

Sheet Справочник номенклатуры
A1: Код товара | B1: Наименование товара | C1: Категория | D1: Ед. изм. | E1: Цена закупки (руб.) | F1: Цена продажи (руб.) | G1: Минимальный остаток (шт.) | H1: Наценка, %
A2: Т-001 | B2: Мука пшеничная | C2: Сырьё | D2: кг | E2: 30 | F2: 35 | G2: 100 | H2: =(F2-E2)/E2*100
A3: Т-002 | B3: Сахар | C3: Сырьё | D3: кг | E3: 40 | F3: 45 | G3: 50 | H3: =(F3-E3)/E3*100
A4: Т-003 | B4: Соль | C4: Сырьё | D4: кг | E4: 15 | F4: 20 | G4: 20 | H4: =(F4-E4)/E4*100
A5: Т-004 | B5: Дрожжи | C5: Сырьё | D5: кг | E5: 100 | F5: 160 | G5: 10 | H5: =(F5-E5)/E5*100
A6: Т-005 | B6: Масло растительное | C6: Сырьё | D6: л | E6: 80 | F6: 130 | G6: 30 | H6: =(F6-E6)/E6*100
A7: Т-006 | B7: Тесто слоеное | C7: Полуфабрикат | D7: кг | E7: 100 | F7: 140 | G7: 20 | H7: =(F7-E7)/E7*100
A8: Т-007 | B8: Фарш мясной | C8: Полуфабрикат | D8: кг | E8: 300 | F8: 400 | G8: 15 | H8: =(F8-E8)/E8*100
A9: Т-008 | B9: Основа для пиццы | C9: Полуфабрикат | D9: шт | E9: 50 | F9: 70 | G9: 30 | H9: =(F9-E9)/E9*100
A10: Т-009 | B10: Бульон | C10: Полуфабрикат | D10: л | E10: 80 | F10: 90 | G10: 10 | H10: =(F10-E10)/E10*100
A11: Т-010 | B11: Начинка ягодная | C11: Полуфабрикат | D11: кг | E11: 150 | F11: 240 | G11: 5 | H11: =(F11-E11)/E11*100
A12: Т-011 | B12: Хлеб белый | C12: Готовая продукция | D12: шт | E12: 20 | F12: 35 | G12: 50 | H12: =(F12-E12)/E12*100
A13: Т-012 | B13: Батон нарезной | C13: Готовая продукция | D13: шт | E13: 25 | F13: 30 | G13: 40 | H13: =(F13-E13)/E13*100
... A21: Т-020 | B21: Средство моющее | C21: Расходные материалы | D21: л | E21: 100 | F21: 115 | G21: 20 | H21: =(F21-E21)/E21*100

Sheet Справочник контрагентов
A1: Код контрагента | B1: Наименование | C1: Тип | D1: ИНН | E1: Город | F1: Телефон | G1: Условия оплаты
A2: К-001 | B2: ООО Мукомол | C2: Поставщик | D2: 7601 | E2: Ярославль | F2: 11-11 | G2: 14
A3: К-002 | B3: ЗАО СахарТорг | C3: Поставщик | D3: 7602 | E3: Рыбинск | F3: 22-22 | G3: 30
A4: К-009 | B4: Супермаркет №1 | C4: Покупатель | D4: 7609 | E4: Ярославль | F4: 99-99 | G4: 14
A5: К-010 | B5: Сеть Магазинов У Дома | C5: Покупатель | D5: 7610 | E5: Рыбинск | F5: 10-10 | G5: 21
A6: К-011 | B6: ИП Петров П.П. | C6: Покупатель | D6: 7611 | E6: Кострома | F6: 65-43 | G6: 5
A7: К-012 | B7: ООО Ресторан Люкс | C7: Покупатель | D7: 7612 | E7: Ярославль | F7: 12-12 | G7: 0
A8: К-013 | B8: Кафе Снежинка | C8: Покупатель | D8: 7613 | E8: Тутаев | F8: 13-13 | G8: 7
A9: К-014 | B9: Столовая Завода | C9: Покупатель | D9: 7614 | E9: Ярославль | F9: 14-14 | G9: 30
A10: К-015 | B10: ООО Пекарня | C10: Покупатель | D10: 7615 | E10: Москва | F10: 15-15 | G10: 14

Sheet Заказы
A1: № заказа | B1: Дата заказа | C1: Клиент | D1: Код товара | E1: Наименование | F1: Количество (шт.) | G1: Цена | H1: Сумма | I1: Скидка % | J1: Сумма со скидкой | K1: Статус заказа
A2: З-001 | B2: 08.11.2026 | C2: Супермаркет №1 | D2: Т-001 | E2: =VLOOKUP(D2,'Справочник номенклатуры'!A:B,2,FALSE) | F2: 9 | G2: =VLOOKUP(D2,'Справочник номенклатуры'!A:F,6,FALSE) | H2: =F2*G2 | I2: 1 | J2: =H2*(1-I2/100) | K2: Отменён
A3: З-002 | B3: 15.11.2026 | C3: ООО Пекарня | D3: Т-010 | E3: =VLOOKUP(D3,'Справочник номенклатуры'!A:B,2,FALSE) | F3: 19 | G3: =VLOOKUP(D3,'Справочник номенклатуры'!A:F,6,FALSE) | H3: =F3*G3 | I3: 10 | J3: =H3*(1-I3/100) | K3: В обработке
A4: З-003 | B4: 01.11.2026 | C4: ООО Пекарня | D4: Т-017 | E4: =VLOOKUP(D4,'Справочник номенклатуры'!A:B,2,FALSE) | F4: 14 | G4: =VLOOKUP(D4,'Справочник номенклатуры'!A:F,6,FALSE) | H4: =F4*G4 | I4: 10 | J4: =H4*(1-I4/100) | K4: В обработке
A5: З-004 | B5: 11.11.2026 | C5: ООО Пекарня | D5: Т-008 | E5: =VLOOKUP(D5,'Справочник номенклатуры'!A:B,2,FALSE) | F5: 11 | G5: =VLOOKUP(D5,'Справочник номенклатуры'!A:F,6,FALSE) | H5: =F5*G5 | I5: 9 | J5: =H5*(1-I5/100) | K5: Отменён
A6: З-005 | B6: 06.11.2026 | C6: ИП Петров П.П. | D6: Т-003 | E6: =VLOOKUP(D6,'Справочник номенклатуры'!A:B,2,FALSE) | F6: 32 | G6: =VLOOKUP(D6,'Справочник номенклатуры'!A:F,6,FALSE) | H6: =F6*G6 | I6: 8 | J6: =H6*(1-I6/100) | K6: Отгружен
A7: З-006 | B7: 05.11.2026 | C7: Супермаркет №1 | D7: Т-001 | E7: =VLOOKUP(D7,'Справочник номенклатуры'!A:B,2,FALSE) | F7: 38 | G7: =VLOOKUP(D7,'Справочник номенклатуры'!A:F,6,FALSE) | H7: =F7*G7 | I7: 3 | J7: =H7*(1-I7/100) | K7: Отменён
A8: З-007 | B8: 12.11.2026 | C8: Супермаркет №1 | D8: Т-001 | E8: =VLOOKUP(D8,'Справочник номенклатуры'!A:B,2,FALSE) | F8: 8 | G8: =VLOOKUP(D8,'Справочник номенклатуры'!A:F,6,FALSE) | H8: =F8*G8 | I8: 15 | J8: =H8*(1-I8/100) | K8: Отгружен
A9: З-008 | B9: 04.11.2026 | C9: Сеть Магазинов У Дома | D9: Т-019 | E9: =VLOOKUP(D9,'Справочник номенклатуры'!A:B,2,FALSE) | F9: 21 | G9: =VLOOKUP(D9,'Справочник номенклатуры'!A:F,6,FALSE) | H9: =F9*G9 | I9: 14 | J9: =H9*(1-I9/100) | K9: Отгружен
A10: З-009 | B10: 01.11.2026 | C10: Супермаркет №1 | D10: Т-012 | E10: =VLOOKUP(D10,'Справочник номенклатуры'!A:B,2,FALSE) | F10: 48 | G10: =VLOOKUP(D10,'Справочник номенклатуры'!A:F,6,FALSE) | H10: =F10*G10 | I10: 12 | J10: =H10*(1-I10/100) | K10: Отменён
A11: З-010 | B11: 10.11.2026 | C11: Столовая Завода | D11: Т-006 | E11: =VLOOKUP(D11,'Справочник номенклатуры'!A:B,2,FALSE) | F11: 26 | G11: =VLOOKUP(D11,'Справочник номенклатуры'!A:F,6,FALSE) | H11: =F11*G11 | I11: 1 | J11: =H11*(1-I11/100) | K11: Отменён
A12: З-011 | B12: 01.11.2026 | C12: ИП Петров П.П. | D12: Т-015 | E12: =VLOOKUP(D12,'Справочник номенклатуры'!A:B,2,FALSE) | F12: 44 | G12: =VLOOKUP(D12,'Справочник номенклатуры'!A:F,6,FALSE) | H12: =F12*G12 | I12: 7 | J12: =H12*(1-I12/100) | K12: Отменён
A13: З-012 | B13: 04.11.2026 | C13: ООО Ресторан Люкс | D13: Т-007 | E13: =VLOOKUP(D13,'Справочник номенклатуры'!A:B,2,FALSE) | F13: 32 | G13: =VLOOKUP(D13,'Справочник номенклатуры'!A:F,6,FALSE) | H13: =F13*G13 | I13: 7 | J13: =H13*(1-I13/100) | K13: Отгружен
... A21: З-020 | B21: 12.11.2026 | C21: ООО Ресторан Люкс | D21: Т-014 | E21: =VLOOKUP(D21,'Справочник номенклатуры'!A:B,2,FALSE) | F21: 30 | G21: =VLOOKUP(D21,'Справочник номенклатуры'!A:F,6,FALSE) | H21: =F21*G21 | I21: 9 | J21: =H21*(1-I21/100) | K21: Отменён

Sheet Анализ продаж
A1: ВНИМАНИЕ!
A2: Сводные таблицы (Pivot Tables) в Excel требуют интерактивности,
A3: которую лучше создавать вручную встроенными средствами Excel.
A5: Инструкция по созданию 1-й сводной таблицы:
A6: 1. Перейдите на лист 'Заказы', выделите всю таблицу (A1:K21)
A7: 2. Вставка -> Сводная таблица -> На существующий лист (выберите лист 'Анализ продаж')
A8: 3. В 'Строки' перетащите 'Клиент'
A9: 4. В 'Значения' перетащите 'Сумма со скидкой' и 'Количество заказов' (или любой текст для подсчета количества)
A10: 5. Анализ сводной таблицы -> Поля, элементы и наборы -> Вычисляемое поле.
A11: Имя: 'Средний чек', Формула: '= Сумма со скидкой / Количество заказов'
