Workbook

Sheet Справочник номенклатуры
A1: Код товара | B1: Наименование товара | C1: Категория | D1: Ед. изм. | E1: Цена закупки | F1: Цена продажи | G1: Мин. остаток | H1: Наценка, %
A2: Т-001 | B2: Доска | C2: Сырьё | D2: м | E2: 300 | F2: 450 | G2: 100 | H2: =(F2-E2)/E2*100
A3: Т-002 | B3: Ножка | C3: Полуфабрикат | D3: шт | E3: 150 | F3: 200 | G3: 50 | H3: =(F3-E3)/E3*100
A4: Т-003 | B4: Шуруп | C4: Расходные материалы | D4: шт | E4: 2 | F4: 5 | G4: 500 | H4: =(F4-E4)/E4*100
A5: Т-004 | B5: Сиденье | C5: Полуфабрикат | D5: шт | E5: 300 | F5: 400 | G5: 30 | H5: =(F5-E5)/E5*100
A6: Т-005 | B6: Петля | C6: Расходные материалы | D6: шт | E6: 15 | F6: 25 | G6: 200 | H6: =(F6-E6)/E6*100
A7: Т-006 | B7: Стол | C7: Готовая продукция | D7: шт | E7: 1500 | F7: 3000 | G7: 10 | H7: =(F7-E7)/E7*100
A8: Т-007 | B8: Стул | C8: Готовая продукция | D8: шт | E8: 800 | F8: 1500 | G8: 20 | H8: =(F8-E8)/E8*100
A9: Т-008 | B9: Шкаф | C9: Готовая продукция | D9: шт | E9: 4000 | F9: 8000 | G9: 5 | H9: =(F9-E9)/E9*100

Sheet Справочник контрагентов
A1: Код контрагента | B1: Наименование | C1: Тип | D1: ИНН | E1: Город | F1: Телефон | G1: Условия оплаты
A2: К-001 | B2: ООО ЛесПром | C2: Поставщик | D2: 7601 | E2: Ярославль | F2: 11-11 | G2: 14
A3: К-002 | B3: ЗАО Метиз | C3: Поставщик | D3: 7602 | E3: Рыбинск | F3: 22-22 | G3: 30
A4: К-003 | B4: МебельТорг | C4: Покупатель | D4: 7603 | E4: Москва | F4: 33-33 | G4: 14
A5: К-004 | B5: ИП Иванов | C5: Покупатель | D5: 7604 | E5: Кострома | F5: 44-44 | G5: 7

Sheet Приходные ордера
A1: № ордера | B1: Дата | C1: Код товара | D1: Наименование | E1: Кол-во | F1: Поставщик | G1: Цена закупки | H1: Сумма
A2: ПО-001 | B2: 01.10.2026 | C2: Т-001 | D2: =VLOOKUP(C2,'Справочник номенклатуры'!A:B,2,FALSE) | E2: 56 | F2: ЗАО Метиз | G2: =VLOOKUP(C2,'Справочник номенклатуры'!A:E,5,FALSE) | H2: =E2*G2
A3: ПО-002 | B3: 01.10.2026 | C3: Т-002 | D3: =VLOOKUP(C3,'Справочник номенклатуры'!A:B,2,FALSE) | E3: 107 | F3: ООО ЛесПром | G3: =VLOOKUP(C3,'Справочник номенклатуры'!A:E,5,FALSE) | H3: =E3*G3
A4: ПО-003 | B4: 01.10.2026 | C4: Т-001 | D4: =VLOOKUP(C4,'Справочник номенклатуры'!A:B,2,FALSE) | E4: 189 | F4: ООО ЛесПром | G4: =VLOOKUP(C4,'Справочник номенклатуры'!A:E,5,FALSE) | H4: =E4*G4
A5: ПО-004 | B5: 01.10.2026 | C5: Т-005 | D5: =VLOOKUP(C5,'Справочник номенклатуры'!A:B,2,FALSE) | E5: 158 | F5: ООО ЛесПром | G5: =VLOOKUP(C5,'Справочник номенклатуры'!A:E,5,FALSE) | H5: =E5*G5
A6: ПО-005 | B6: 01.10.2026 | C6: Т-001 | D6: =VLOOKUP(C6,'Справочник номенклатуры'!A:B,2,FALSE) | E6: 73 | F6: ООО ЛесПром | G6: =VLOOKUP(C6,'Справочник номенклатуры'!A:E,5,FALSE) | H6: =E6*G6
A7: ПО-006 | B7: 01.10.2026 | C7: Т-002 | D7: =VLOOKUP(C7,'Справочник номенклатуры'!A:B,2,FALSE) | E7: 179 | F7: ООО ЛесПром | G7: =VLOOKUP(C7,'Справочник номенклатуры'!A:E,5,FALSE) | H7: =E7*G7
A8: ПО-007 | B8: 01.10.2026 | C8: Т-005 | D8: =VLOOKUP(C8,'Справочник номенклатуры'!A:B,2,FALSE) | E8: 100 | F8: ЗАО Метиз | G8: =VLOOKUP(C8,'Справочник номенклатуры'!A:E,5,FALSE) | H8: =E8*G8
A9: ПО-008 | B9: 01.10.2026 | C9: Т-002 | D9: =VLOOKUP(C9,'Справочник номенклатуры'!A:B,2,FALSE) | E9: 164 | F9: ЗАО Метиз | G9: =VLOOKUP(C9,'Справочник номенклатуры'!A:E,5,FALSE) | H9: =E9*G9
A10: ПО-009 | B10: 01.10.2026 | C10: Т-001 | D10: =VLOOKUP(C10,'Справочник номенклатуры'!A:B,2,FALSE) | E10: 90 | F10: ЗАО Метиз | G10: =VLOOKUP(C10,'Справочник номенклатуры'!A:E,5,FALSE) | H10: =E10*G10
A11: ПО-010 | B11: 01.10.2026 | C11: Т-003 | D11: =VLOOKUP(C11,'Справочник номенклатуры'!A:B,2,FALSE) | E11: 121 | F11: ООО ЛесПром | G11: =VLOOKUP(C11,'Справочник номенклатуры'!A:E,5,FALSE) | H11: =E11*G11
A12: ПО-011 | B12: 01.10.2026 | C12: Т-002 | D12: =VLOOKUP(C12,'Справочник номенклатуры'!A:B,2,FALSE) | E12: 136 | F12: ООО ЛесПром | G12: =VLOOKUP(C12,'Справочник номенклатуры'!A:E,5,FALSE) | H12: =E12*G12
A13: ПО-012 | B13: 01.10.2026 | C13: Т-001 | D13: =VLOOKUP(C13,'Справочник номенклатуры'!A:B,2,FALSE) | E13: 147 | F13: ООО ЛесПром | G13: =VLOOKUP(C13,'Справочник номенклатуры'!A:E,5,FALSE) | H13: =E13*G13
... A16: ПО-015 | B16: 01.10.2026 | C16: Т-004 | D16: =VLOOKUP(C16,'Справочник номенклатуры'!A:B,2,FALSE) | E16: 70 | F16: ЗАО Метиз | G16: =VLOOKUP(C16,'Справочник номенклатуры'!A:E,5,FALSE) | H16: =E16*G16

Sheet Расходные ордера
A1: № ордера | B1: Дата | C1: Код товара | D1: Наименование | E1: Кол-во | F1: Покупатель | G1: Цена продажи | H1: Сумма
A2: РО-001 | B2: 05.10.2026 | C2: Т-008 | D2: =VLOOKUP(C2,'Справочник номенклатуры'!A:B,2,FALSE) | E2: 16 | F2: МебельТорг | G2: =VLOOKUP(C2,'Справочник номенклатуры'!A:F,6,FALSE) | H2: =E2*G2
A3: РО-002 | B3: 05.10.2026 | C3: Т-008 | D3: =VLOOKUP(C3,'Справочник номенклатуры'!A:B,2,FALSE) | E3: 7 | F3: МебельТорг | G3: =VLOOKUP(C3,'Справочник номенклатуры'!A:F,6,FALSE) | H3: =E3*G3
A4: РО-003 | B4: 05.10.2026 | C4: Т-008 | D4: =VLOOKUP(C4,'Справочник номенклатуры'!A:B,2,FALSE) | E4: 12 | F4: ИП Иванов | G4: =VLOOKUP(C4,'Справочник номенклатуры'!A:F,6,FALSE) | H4: =E4*G4
A5: РО-004 | B5: 05.10.2026 | C5: Т-006 | D5: =VLOOKUP(C5,'Справочник номенклатуры'!A:B,2,FALSE) | E5: 12 | F5: МебельТорг | G5: =VLOOKUP(C5,'Справочник номенклатуры'!A:F,6,FALSE) | H5: =E5*G5
A6: РО-005 | B6: 05.10.2026 | C6: Т-007 | D6: =VLOOKUP(C6,'Справочник номенклатуры'!A:B,2,FALSE) | E6: 13 | F6: ИП Иванов | G6: =VLOOKUP(C6,'Справочник номенклатуры'!A:F,6,FALSE) | H6: =E6*G6
A7: РО-006 | B7: 05.10.2026 | C7: Т-008 | D7: =VLOOKUP(C7,'Справочник номенклатуры'!A:B,2,FALSE) | E7: 16 | F7: МебельТорг | G7: =VLOOKUP(C7,'Справочник номенклатуры'!A:F,6,FALSE) | H7: =E7*G7
A8: РО-007 | B8: 05.10.2026 | C8: Т-007 | D8: =VLOOKUP(C8,'Справочник номенклатуры'!A:B,2,FALSE) | E8: 16 | F8: МебельТорг | G8: =VLOOKUP(C8,'Справочник номенклатуры'!A:F,6,FALSE) | H8: =E8*G8
A9: РО-008 | B9: 05.10.2026 | C9: Т-008 | D9: =VLOOKUP(C9,'Справочник номенклатуры'!A:B,2,FALSE) | E9: 13 | F9: МебельТорг | G9: =VLOOKUP(C9,'Справочник номенклатуры'!A:F,6,FALSE) | H9: =E9*G9
A10: РО-009 | B10: 05.10.2026 | C10: Т-008 | D10: =VLOOKUP(C10,'Справочник номенклатуры'!A:B,2,FALSE) | E10: 10 | F10: МебельТорг | G10: =VLOOKUP(C10,'Справочник номенклатуры'!A:F,6,FALSE) | H10: =E10*G10
A11: РО-010 | B11: 05.10.2026 | C11: Т-006 | D11: =VLOOKUP(C11,'Справочник номенклатуры'!A:B,2,FALSE) | E11: 19 | F11: ИП Иванов | G11: =VLOOKUP(C11,'Справочник номенклатуры'!A:F,6,FALSE) | H11: =E11*G11
A12: РО-011 | B12: 05.10.2026 | C12: Т-007 | D12: =VLOOKUP(C12,'Справочник номенклатуры'!A:B,2,FALSE) | E12: 12 | F12: ИП Иванов | G12: =VLOOKUP(C12,'Справочник номенклатуры'!A:F,6,FALSE) | H12: =E12*G12
A13: РО-012 | B13: 05.10.2026 | C13: Т-006 | D13: =VLOOKUP(C13,'Справочник номенклатуры'!A:B,2,FALSE) | E13: 12 | F13: МебельТорг | G13: =VLOOKUP(C13,'Справочник номенклатуры'!A:F,6,FALSE) | H13: =E13*G13
... A16: РО-015 | B16: 05.10.2026 | C16: Т-006 | D16: =VLOOKUP(C16,'Справочник номенклатуры'!A:B,2,FALSE) | E16: 20 | F16: ИП Иванов | G16: =VLOOKUP(C16,'Справочник номенклатуры'!A:F,6,FALSE) | H16: =E16*G16

Sheet Остатки
A1: Код товара | B1: Наименование | C1: Нач. остаток | D1: Приход | E1: Расход | F1: Конечный остаток | G1: Мин. остаток | H1: Статус
A2: Т-001 | B2: =VLOOKUP(A2,'Справочник номенклатуры'!A:B,2,FALSE) | C2: 50 | D2: =SUMIF('Приходные ордера'!C:C, A2, 'Приходные ордера'!E:E) | E2: =SUMIF('Расходные ордера'!C:C, A2, 'Расходные ордера'!E:E) | F2: =C2+D2-E2 | G2: =VLOOKUP(A2,'Справочник номенклатуры'!A:G,7,FALSE) | H2: =IF(F2<G2,"Заказать","ОК")
A3: Т-002 | B3: =VLOOKUP(A3,'Справочник номенклатуры'!A:B,2,FALSE) | C3: 50 | D3: =SUMIF('Приходные ордера'!C:C, A3, 'Приходные ордера'!E:E) | E3: =SUMIF('Расходные ордера'!C:C, A3, 'Расходные ордера'!E:E) | F3: =C3+D3-E3 | G3: =VLOOKUP(A3,'Справочник номенклатуры'!A:G,7,FALSE) | H3: =IF(F3<G3,"Заказать","ОК")
A4: Т-003 | B4: =VLOOKUP(A4,'Справочник номенклатуры'!A:B,2,FALSE) | C4: 50 | D4: =SUMIF('Приходные ордера'!C:C, A4, 'Приходные ордера'!E:E) | E4: =SUMIF('Расходные ордера'!C:C, A4, 'Расходные ордера'!E:E) | F4: =C4+D4-E4 | G4: =VLOOKUP(A4,'Справочник номенклатуры'!A:G,7,FALSE) | H4: =IF(F4<G4,"Заказать","ОК")
A5: Т-004 | B5: =VLOOKUP(A5,'Справочник номенклатуры'!A:B,2,FALSE) | C5: 50 | D5: =SUMIF('Приходные ордера'!C:C, A5, 'Приходные ордера'!E:E) | E5: =SUMIF('Расходные ордера'!C:C, A5, 'Расходные ордера'!E:E) | F5: =C5+D5-E5 | G5: =VLOOKUP(A5,'Справочник номенклатуры'!A:G,7,FALSE) | H5: =IF(F5<G5,"Заказать","ОК")
A6: Т-005 | B6: =VLOOKUP(A6,'Справочник номенклатуры'!A:B,2,FALSE) | C6: 50 | D6: =SUMIF('Приходные ордера'!C:C, A6, 'Приходные ордера'!E:E) | E6: =SUMIF('Расходные ордера'!C:C, A6, 'Расходные ордера'!E:E) | F6: =C6+D6-E6 | G6: =VLOOKUP(A6,'Справочник номенклатуры'!A:G,7,FALSE) | H6: =IF(F6<G6,"Заказать","ОК")
A7: Т-006 | B7: =VLOOKUP(A7,'Справочник номенклатуры'!A:B,2,FALSE) | C7: 50 | D7: =SUMIF('Приходные ордера'!C:C, A7, 'Приходные ордера'!E:E) | E7: =SUMIF('Расходные ордера'!C:C, A7, 'Расходные ордера'!E:E) | F7: =C7+D7-E7 | G7: =VLOOKUP(A7,'Справочник номенклатуры'!A:G,7,FALSE) | H7: =IF(F7<G7,"Заказать","ОК")
A8: Т-007 | B8: =VLOOKUP(A8,'Справочник номенклатуры'!A:B,2,FALSE) | C8: 50 | D8: =SUMIF('Приходные ордера'!C:C, A8, 'Приходные ордера'!E:E) | E8: =SUMIF('Расходные ордера'!C:C, A8, 'Расходные ордера'!E:E) | F8: =C8+D8-E8 | G8: =VLOOKUP(A8,'Справочник номенклатуры'!A:G,7,FALSE) | H8: =IF(F8<G8,"Заказать","ОК")
A9: Т-008 | B9: =VLOOKUP(A9,'Справочник номенклатуры'!A:B,2,FALSE) | C9: 50 | D9: =SUMIF('Приходные ордера'!C:C, A9, 'Приходные ордера'!E:E) | E9: =SUMIF('Расходные ордера'!C:C, A9, 'Расходные ордера'!E:E) | F9: =C9+D9-E9 | G9: =VLOOKUP(A9,'Справочник номенклатуры'!A:G,7,FALSE) | H9: =IF(F9<G9,"Заказать","ОК")

Sheet Заказы
A1: № заказа | B1: Дата | C1: Клиент | D1: Код товара | E1: Наименование | F1: Кол-во | G1: Цена | H1: Сумма | I1: Скидка % | J1: Сумма со скидкой | K1: Статус
A2: З-001 | B2: 10.11.2026 | C2: ИП Иванов | D2: Т-006 | E2: =VLOOKUP(D2,'Справочник номенклатуры'!A:B,2,FALSE) | F2: 5 | G2: =VLOOKUP(D2,'Справочник номенклатуры'!A:F,6,FALSE) | H2: =F2*G2 | I2: 2 | J2: =H2*(1-I2/100) | K2: Отгружен
A3: З-002 | B3: 10.11.2026 | C3: МебельТорг | D3: Т-008 | E3: =VLOOKUP(D3,'Справочник номенклатуры'!A:B,2,FALSE) | F3: 9 | G3: =VLOOKUP(D3,'Справочник номенклатуры'!A:F,6,FALSE) | H3: =F3*G3 | I3: 8 | J3: =H3*(1-I3/100) | K3: Отгружен
A4: З-003 | B4: 10.11.2026 | C4: ИП Иванов | D4: Т-008 | E4: =VLOOKUP(D4,'Справочник номенклатуры'!A:B,2,FALSE) | F4: 10 | G4: =VLOOKUP(D4,'Справочник номенклатуры'!A:F,6,FALSE) | H4: =F4*G4 | I4: 6 | J4: =H4*(1-I4/100) | K4: Отгружен
A5: З-004 | B5: 10.11.2026 | C5: ИП Иванов | D5: Т-007 | E5: =VLOOKUP(D5,'Справочник номенклатуры'!A:B,2,FALSE) | F5: 4 | G5: =VLOOKUP(D5,'Справочник номенклатуры'!A:F,6,FALSE) | H5: =F5*G5 | I5: 2 | J5: =H5*(1-I5/100) | K5: Отгружен
A6: З-005 | B6: 10.11.2026 | C6: ИП Иванов | D6: Т-006 | E6: =VLOOKUP(D6,'Справочник номенклатуры'!A:B,2,FALSE) | F6: 1 | G6: =VLOOKUP(D6,'Справочник номенклатуры'!A:F,6,FALSE) | H6: =F6*G6 | I6: 1 | J6: =H6*(1-I6/100) | K6: Отгружен
A7: З-006 | B7: 10.11.2026 | C7: МебельТорг | D7: Т-008 | E7: =VLOOKUP(D7,'Справочник номенклатуры'!A:B,2,FALSE) | F7: 3 | G7: =VLOOKUP(D7,'Справочник номенклатуры'!A:F,6,FALSE) | H7: =F7*G7 | I7: 10 | J7: =H7*(1-I7/100) | K7: Отгружен
A8: З-007 | B8: 10.11.2026 | C8: ИП Иванов | D8: Т-008 | E8: =VLOOKUP(D8,'Справочник номенклатуры'!A:B,2,FALSE) | F8: 2 | G8: =VLOOKUP(D8,'Справочник номенклатуры'!A:F,6,FALSE) | H8: =F8*G8 | I8: 6 | J8: =H8*(1-I8/100) | K8: Отгружен
A9: З-008 | B9: 10.11.2026 | C9: ИП Иванов | D9: Т-008 | E9: =VLOOKUP(D9,'Справочник номенклатуры'!A:B,2,FALSE) | F9: 8 | G9: =VLOOKUP(D9,'Справочник номенклатуры'!A:F,6,FALSE) | H9: =F9*G9 | I9: 8 | J9: =H9*(1-I9/100) | K9: Отгружен
A10: З-009 | B10: 10.11.2026 | C10: ИП Иванов | D10: Т-008 | E10: =VLOOKUP(D10,'Справочник номенклатуры'!A:B,2,FALSE) | F10: 1 | G10: =VLOOKUP(D10,'Справочник номенклатуры'!A:F,6,FALSE) | H10: =F10*G10 | I10: 10 | J10: =H10*(1-I10/100) | K10: Отгружен
A11: З-010 | B11: 10.11.2026 | C11: МебельТорг | D11: Т-008 | E11: =VLOOKUP(D11,'Справочник номенклатуры'!A:B,2,FALSE) | F11: 9 | G11: =VLOOKUP(D11,'Справочник номенклатуры'!A:F,6,FALSE) | H11: =F11*G11 | I11: 4 | J11: =H11*(1-I11/100) | K11: Отгружен
A12: З-011 | B12: 10.11.2026 | C12: ИП Иванов | D12: Т-006 | E12: =VLOOKUP(D12,'Справочник номенклатуры'!A:B,2,FALSE) | F12: 5 | G12: =VLOOKUP(D12,'Справочник номенклатуры'!A:F,6,FALSE) | H12: =F12*G12 | I12: 6 | J12: =H12*(1-I12/100) | K12: Отгружен
A13: З-012 | B13: 10.11.2026 | C13: МебельТорг | D13: Т-007 | E13: =VLOOKUP(D13,'Справочник номенклатуры'!A:B,2,FALSE) | F13: 1 | G13: =VLOOKUP(D13,'Справочник номенклатуры'!A:F,6,FALSE) | H13: =F13*G13 | I13: 4 | J13: =H13*(1-I13/100) | K13: Отгружен
... A21: З-020 | B21: 10.11.2026 | C21: МебельТорг | D21: Т-006 | E21: =VLOOKUP(D21,'Справочник номенклатуры'!A:B,2,FALSE) | F21: 8 | G21: =VLOOKUP(D21,'Справочник номенклатуры'!A:F,6,FALSE) | H21: =F21*G21 | I21: 8 | J21: =H21*(1-I21/100) | K21: Отгружен

Sheet Спецификации
A1: Код изделия | B1: Изделие | C1: Код компонента | D1: Компонент | E1: Кол-во на ед.
A2: Т-006 | B2: Стол | C2: Т-001 | D2: Доска | E2: 5
A3: Т-006 | B3: Стол | C3: Т-002 | D3: Ножка | E3: 4
A4: Т-006 | B4: Стол | C4: Т-003 | D4: Шуруп | E4: 20

Sheet План производства
A1: Код изделия | B1: Наименование | C1: Неделя 1 | D1: Неделя 2 | E1: Неделя 3 | F1: Неделя 4 | G1: Итого
A2: Т-006 | B2: Стол | C2: 10 | D2: 15 | E2: 10 | F2: 20 | G2: =SUM(C2:F2)

Sheet Потребность в компонентах
A1: Код компонента | B1: Наименование | C1: Потребность | D1: Текущий остаток | E1: Закупить | F1: Цена | G1: Сумма закупки
A2: Т-001 | B2: Доска | C2: =SUMPRODUCT('План производства'!G2*'Спецификации'!E2) | D2: =VLOOKUP(A2,'Остатки'!A:F,6,FALSE) | E2: =MAX(0, C2-D2) | F2: =VLOOKUP(A2,'Справочник номенклатуры'!A:E,5,FALSE) | G2: =E2*F2

Sheet Бюджет продаж
A1: Показатель | B1: Q1 | C1: Q2 | D1: Q3 | E1: Q4 | F1: Итого
A2: Объём продаж (шт) | B2: 1000 | C2: 1200 | D2: 1500 | E2: 1300 | F2: =SUM(B2:E2)
A3: Цена (руб) | B3: 500 | C3: 500 | D3: 500 | E3: 500
A4: Выручка | B4: =B2*B3 | C4: =C2*C3 | D4: =D2*D3 | E4: =E2*E3 | F4: =SUM(B4:E4)

Sheet Реализация (Дебиторка)
A1: № док | B1: Дата отгрузки | C1: Клиент | D1: Сумма | E1: Условия оплаты | F1: Плановая дата | G1: Факт дата | H1: Дни просрочки | I1: Статус
A2: Р-001 | B2: 01.09.2026 | C2: МебельТорг | D2: 27370 | E2: =VLOOKUP(C2,'Справочник контрагентов'!B:G,6,FALSE) | F2: =B2+E2 | H2: =IF(G2="", TODAY()-F2, G2-F2) | I2: =IF(G2="", IF(H2>0, "Просрочена", "Ожидается"), "Оплачена")
A3: Р-002 | B3: 01.09.2026 | C3: ИП Иванов | D3: 23880 | E3: =VLOOKUP(C3,'Справочник контрагентов'!B:G,6,FALSE) | F3: =B3+E3 | H3: =IF(G3="", TODAY()-F3, G3-F3) | I3: =IF(G3="", IF(H3>0, "Просрочена", "Ожидается"), "Оплачена")
A4: Р-003 | B4: 01.09.2026 | C4: МебельТорг | D4: 30428 | E4: =VLOOKUP(C4,'Справочник контрагентов'!B:G,6,FALSE) | F4: =B4+E4 | H4: =IF(G4="", TODAY()-F4, G4-F4) | I4: =IF(G4="", IF(H4>0, "Просрочена", "Ожидается"), "Оплачена")
A5: Р-004 | B5: 01.09.2026 | C5: ИП Иванов | D5: 34472 | E5: =VLOOKUP(C5,'Справочник контрагентов'!B:G,6,FALSE) | F5: =B5+E5 | H5: =IF(G5="", TODAY()-F5, G5-F5) | I5: =IF(G5="", IF(H5>0, "Просрочена", "Ожидается"), "Оплачена")
A6: Р-005 | B6: 01.09.2026 | C6: ИП Иванов | D6: 43919 | E6: =VLOOKUP(C6,'Справочник контрагентов'!B:G,6,FALSE) | F6: =B6+E6 | H6: =IF(G6="", TODAY()-F6, G6-F6) | I6: =IF(G6="", IF(H6>0, "Просрочена", "Ожидается"), "Оплачена")
A7: Р-006 | B7: 01.09.2026 | C7: ИП Иванов | D7: 17930 | E7: =VLOOKUP(C7,'Справочник контрагентов'!B:G,6,FALSE) | F7: =B7+E7 | H7: =IF(G7="", TODAY()-F7, G7-F7) | I7: =IF(G7="", IF(H7>0, "Просрочена", "Ожидается"), "Оплачена")
A8: Р-007 | B8: 01.09.2026 | C8: МебельТорг | D8: 24725 | E8: =VLOOKUP(C8,'Справочник контрагентов'!B:G,6,FALSE) | F8: =B8+E8 | H8: =IF(G8="", TODAY()-F8, G8-F8) | I8: =IF(G8="", IF(H8>0, "Просрочена", "Ожидается"), "Оплачена")
A9: Р-008 | B9: 01.09.2026 | C9: МебельТорг | D9: 32156 | E9: =VLOOKUP(C9,'Справочник контрагентов'!B:G,6,FALSE) | F9: =B9+E9 | H9: =IF(G9="", TODAY()-F9, G9-F9) | I9: =IF(G9="", IF(H9>0, "Просрочена", "Ожидается"), "Оплачена")
A10: Р-009 | B10: 01.09.2026 | C10: МебельТорг | D10: 48555 | E10: =VLOOKUP(C10,'Справочник контрагентов'!B:G,6,FALSE) | F10: =B10+E10 | H10: =IF(G10="", TODAY()-F10, G10-F10) | I10: =IF(G10="", IF(H10>0, "Просрочена", "Ожидается"), "Оплачена")

Sheet Сотрудники
A1: Таб. № | B1: ФИО | C1: Должность | D1: Отдел | E1: Оклад | F1: Дата приёма | G1: Стаж
A2: С-001 | B2: Иванов И.И. | C2: Менеджер | D2: Отдел продаж | E2: 50000 | F2: 01.01.2020 | G2: =ROUND(YEARFRAC(F2, TODAY()), 1)

Sheet Расчёт ЗП
A1: Таб. № | B1: Отработано | C1: Норма | D1: Начислено | E1: Премия | F1: НДФЛ | G1: К выплате
A2: С-001 | B2: 21 | C2: 21 | D2: =VLOOKUP(A2,'Сотрудники'!A:E,5,FALSE)*B2/C2 | E2: =D2*0.1 | F2: =(D2+E2)*0.13 | G2: =D2+E2-F2

Sheet АВС-анализ
A1: Код товара | B1: Выручка | C1: Доля | D1: Накоп. доля | E1: Класс
A2: Т-006 | B2: =SUMIF('Заказы'!D:D, A2, 'Заказы'!J:J) | C2: =B2/SUM(B:B) | D2: =C2 | E2: =IF(D2<=0.8,"A",IF(D2<=0.95,"B","C"))

Sheet Оценка поставщиков
A1: Поставщик | B1: Цена | C1: Срок | D1: Оплата | E1: Рейтинг | F1: Интегральный показатель
A2: ООО ЛесПром | B2: 100 | C2: 5 | D2: 14 | E2: 8 | F2: =B2*0.4 + C2*100*0.3 + (10-D2)*10 + (10-E2)*1000*0.2

Sheet Дашборд
A1: KPI | B1: Значение
A2: Выручка (ЛР3) | B2: =SUM('Заказы'!J:J)
A3: Стоимость остатков (ЛР2) | B3: =SUMPRODUCT('Остатки'!F:F, 'Справочник номенклатуры'!E:E)
A4: Дебиторка (ЛР6) | B4: =SUMIF('Реализация (Дебиторка)'!I:I, "Просрочена", 'Реализация (Дебиторка)'!D:D)
